{
  "display": {
    "icon": {
      "id": "minecraft:ominous_trial_key",
      "count": 1
    },
    "title": {
      "translate": "item.minecraft.ominous_trial_key"
    },
    "description": {
      "translate": ""
    },
    "announce_to_chat": false,
    "hidden": false
  },
  "parent": "ic:item_collection/items/ominous_bottle",
  "criteria": {
    "item_collection": {
      "trigger": "minecraft:inventory_changed",
      "conditions": {
        "items": [
          {
            "items": "minecraft:ominous_trial_key"
          }
        ]
      }
    }
  },
  "requirements": [
    [
      "item_collection"
    ]
  ]
}